{
    "master": false,
    "tls": false,
    "port": "9991",
    "rate_limit": 1,
	"rate_burst": 1,
    "api_key": "my_secret_key",
    "clients:": [
        {
            "alias": "client1",
            "os": [
                {
                    "name": "Windows",
                    "boot_id": "0000"
                },
                {
                    "name": "ubuntu",
                    "boot_id": "0002"
                }
            ]
        },
        {
            "alias": "client2",
            "os": [
                {
                    "name": "Windows",
                    "boot_id": "0001"
                }
            ]
        }
    ]
}